odoo/addons/report_partner_address/README.rst
odoo/addons/report_partner_address/__init__.py
odoo/addons/report_partner_address/__manifest__.py
odoo/addons/report_partner_address/i18n/ja.po
odoo/addons/report_partner_address/i18n/report_partner_address.pot
odoo/addons/report_partner_address/models/__init__.py
odoo/addons/report_partner_address/models/res_partner.py
odoo/addons/report_partner_address/readme/CONTRIBUTORS.md
odoo/addons/report_partner_address/readme/DESCRIPTION.md
odoo/addons/report_partner_address/readme/USAGE.md
odoo/addons/report_partner_address/static/description/icon.png
odoo/addons/report_partner_address/static/description/index.html
odoo/addons/report_partner_address/tests/__init__.py
odoo/addons/report_partner_address/tests/test_report_partner_address.py
odoo/addons/report_partner_address/views/ir_qweb_widget_templates.xml
odoo/addons/report_partner_address/views/res_partner_views.xml
odoo_addon_report_partner_address-16.0.1.0.0.2.dist-info/METADATA
odoo_addon_report_partner_address-16.0.1.0.0.2.dist-info/WHEEL
odoo_addon_report_partner_address-16.0.1.0.0.2.dist-info/top_level.txt
odoo_addon_report_partner_address-16.0.1.0.0.2.dist-info/RECORD
